[
  {
    "levelNumber": 1,
    "mapGrid": [
      "###################################################",
      "#.....<#......#.....................#.............#",
      "#..#####......#..#####..............#.............#",
      "#..#...#......#..#...#..............#.............#",
      "#..#...+......#+##...#..............#.............#",
      "#..#...#.........#...#..............#.............#",
      "#..#####.........##+##..............#####.........#",
      "#...................................#.............#",
      "#..#####..............#####.........#.............#",
      "#..#...#..............#...#.........#.............#",
      "#..#...+..............+...#.........#.............#",
      "#..#...#..............#...#.........#.............#",
      "#..#####..............#####.........#####.........#",
      "#.................................................#",
      "#.............#................................#..#",
      "#.............#................................#..#",
      "###################################################"
    ],
    "monsters": [
      { "name": "Goblin", "position": [5, 5], "health": 10 },
      { "name": "Skeleton", "position": [10, 15], "health": 12 },
      { "name": "Zombie", "position": [8, 18], "health": 15 },
      { "name": "Slime", "position": [12, 25], "health": 5 }
    ],
    "items": [
      { "itemName": "Health Potion", "itemPosition": [6, 6], "itemDescription": "Restores 20 HP." },
      { "itemName": "Sword", "itemPosition": [11, 20], "itemDescription": "A sharp blade." },
      { "itemName": "Gold Coin", "itemPosition": [8, 30], "itemDescription": "Shiny and valuable." }
    ]
  },
  {
    "levelNumber": 2,
    "mapGrid": [
      "################################################## ",
      "#....#>.......#...............#..................# ",
      "#..##########.#.######........#..................# ",
      "#..#...#......#.#....#........#..................# ",
      "#..#...+.....##+###..##.......#..................# ",
      "#..#...#..........#...#.......#..................##",
      "#..#####..........#.###.......#...................#",
      "#.................#.#.............................#",
      "#..################.#######.....#####.............#",
      "#..#......................#######...#.............#",
      "#..#...################...+.....+...+.............#",
      "#..#...#..............#...#######...#.............#",
      "#..#####..............#####.....#####.............#",
      "#.............<...................................#",
      "###################################################"
    ],
    "monsters": [
      { "name": "Orc", "position": [7, 7], "health": 18 },
      { "name": "Bat", "position": [15, 20], "health": 8 },
      { "name": "Slime", "position": [10, 10], "health": 5 },
      { "name": "Wraith", "position": [18, 25], "health": 20 }
    ],
    "items": [
      { "itemName": "Shield", "itemPosition": [10, 10], "itemDescription": "A protective shield." },
      { "itemName": "Magic Scroll", "itemPosition": [20, 15], "itemDescription": "Contains a spell." },
      { "itemName": "Amulet", "itemPosition": [12, 30], "itemDescription": "Grants protection." }
    ]
  },
  {
    "levelNumber": 3,
    "mapGrid": [
      "###################################################",
      "#.............#...................#...............#",
      "#..#####......#..#####............#...............#",
      "#..#...#......#..#...#............#...............#",
      "#..#...+......#+###..#............#...............#",
      "#..#...#......#.#.#...#...........#...............#",
      "#..#####.######.#.#####...........#####...........#",
      "#...............#.................................#",
      "#..#####...######.....#####.......#####...........#",
      "#..#...##+##..........#...#.......#...#...........#",
      "#..#...+.....#####....+...........#...+...........#",
      "#..#<#.#######...######...#.......#...#...........#",
      "#..#####..............#####.......#####...........#",
      "#.................................................#",
      "#.............>...................................#",
      "###################################################"
    ],
    "monsters": [
      { "name": "Dragon", "position": [25, 25], "health": 100 },
      { "name": "Snake", "position": [18, 12], "health": 20 },
      { "name": "Lich", "position": [22, 22], "health": 50 }
    ],
    "items": [
      { "itemName": "Ring of Power", "itemPosition": [10, 10], "itemDescription": "Grants strength." },
      { "itemName": "Potion of Flight", "itemPosition": [15, 15], "itemDescription": "Grants temporary flight." }
    ]
  },
  {
    "levelNumber": 4,
    "mapGrid": [
      "###################################################",
      "#.............#..#..#.............#...............#",
      "#..#####......#..#..##............#...............#",
      "#..#...#......#..##..#............#...............#",
      "#..#...+..........+..##...........#...............#",
      "#..#...#..........#...#...........#...............#",
      "#..#####..........#####...........#####...........#",
      "#.................................................#",
      "#..#####..............#####.......#####...........#",
      "#..#...#..............#...#...#####...#...........#",
      "#..#>..+..............+...#..##...#...+...........#",
      "#..#...#..............#...#.......#...#...........#",
      "#..#####..............###+#######.#####...........#",
      "#.......................#.........................#",
      "###################################################"
    ],
    "monsters": [
      { "name": "Demon", "position": [12, 12], "health": 60 }
    ],
    "items": [
      { "itemName": "Orb of Power", "itemPosition": [10, 10], "itemDescription": "Grants immense power." }
    ]
  }
]
